dash_tailwindcss_plugin/__init__.py
dash_tailwindcss_plugin/cli.py
dash_tailwindcss_plugin/plugin.py
dash_tailwindcss_plugin/utils.py
dash_tailwindcss_plugin-0.1.5.dist-info/licenses/LICENSE
dash_tailwindcss_plugin-0.1.5.dist-info/METADATA
dash_tailwindcss_plugin-0.1.5.dist-info/WHEEL
dash_tailwindcss_plugin-0.1.5.dist-info/entry_points.txt
dash_tailwindcss_plugin-0.1.5.dist-info/top_level.txt
dash_tailwindcss_plugin-0.1.5.dist-info/RECORD
