Metadata-Version: 2.4
Name: dash-tailwindcss-plugin
Version: 0.1.5
Summary: A Dash plugin for integrating TailwindCSS using Dash 3.x hooks
Home-page: https://github.com/HogaStack/dash-tailwindcss-plugin
Author: insistence
Author-email: insistence <3055204202@qq.com>
Project-URL: Homepage, https://github.com/HogaStack/dash-tailwindcss-plugin
Project-URL: Documentation, https://github.com/HogaStack/dash-tailwindcss-plugin
Project-URL: Repository, https://github.com/HogaStack/dash-tailwindcss-plugin
Project-URL: Issues, https://github.com/HogaStack/dash-tailwindcss-plugin/issues
Classifier: Development Status :: 5 - Production/Stable
Classifier: Intended Audience :: Developers
Classifier: License :: OSI Approved :: MIT License
Classifier: Operating System :: OS Independent
Classifier: Programming Language :: Python :: 3
Classifier: Programming Language :: Python :: 3.8
Classifier: Programming Language :: Python :: 3.9
Classifier: Programming Language :: Python :: 3.10
Classifier: Programming Language :: Python :: 3.11
Classifier: Programming Language :: Python :: 3.12
Classifier: Framework :: Dash
Requires-Python: >=3.8
License-File: LICENSE
Requires-Dist: dash>=3.0.3
Provides-Extra: dev
Requires-Dist: build; extra == "dev"
Requires-Dist: twine; extra == "dev"
Provides-Extra: test
Requires-Dist: pytest>=6.0; extra == "test"
Dynamic: author
Dynamic: home-page
Dynamic: license-file
Dynamic: requires-python
